sdrf/__init__.py
sdrf/api_endpoint.py
sdrf/apps.py
sdrf/endpoint_config.py
sdrf/model_endpoint.py
sdrf/swagger_config.py
sdrf/urls.py
sdrf/enums/__init__.py
sdrf/enums/api_data_type_enum.py
sdrf/enums/parameter_type_enum.py
sdrf/utils/settings_utils.py
sdrf-0.1.1.dist-info/LICENSE.txt
sdrf-0.1.1.dist-info/METADATA
sdrf-0.1.1.dist-info/WHEEL
sdrf-0.1.1.dist-info/top_level.txt
sdrf-0.1.1.dist-info/RECORD
