Metadata-Version: 2.1
Name: sdrf
Version: 0.1.1
Summary: Simple rest framework is an abstraction for building rest api with well written documentations
Home-page: https://github.com/hus201/sdrf
Author: Hussein Anabtawi
Author-email: Hussein Anabtawi <husainanabtawi2001@hotmail.com>
Project-URL: Homepage, https://github.com/hus201/sdrf
Project-URL: Bug Tracker, https://github.com/hus201/sdrf/issues
Keywords: sdrf,django,rest apis,swagger,swagger generation,abstraction
Classifier: Programming Language :: Python :: 3
Classifier: License :: OSI Approved :: MIT License
Classifier: Operating System :: OS Independent
Requires-Python: >=3.8, <4
License-File: LICENSE.txt
Requires-Dist: Django (>=4.1.3)
Requires-Dist: djangorestframework (~=3.14.0)
Requires-Dist: drf-yasg
